{
	"dialogue": [
		{
			"speed": 0.03,
			"portrait": "tord",
			"boxState": "normal",
			"expression": "talk",
			"text": "..Dunno where this came from."
		},
		{
			"speed": 0.025,
			"portrait": "tord",
			"boxState": "normal",
			"expression": "talk",
			"text": "Anyways who.. no, WHAT are you?"
		},
		{
			"speed": 0.025,
			"portrait": "bf",
			"boxState": "normal",
			"expression": "talk",
			"text": "bee boo be bop"
		},
		{
			"speed": 0.025,
			"portrait": "tord",
			"boxState": "normal",
			"expression": "talk",
			"text": "Excuse me?"
		},
		{
			"speed": 0.05,
			"portrait": "bf",
			"boxState": "normal",
			"expression": "talk",
			"text": "boo bees"
		},
		{
			"speed": 0.05,
			"portrait": "tord",
			"boxState": "normal",
			"expression": "talk",
			"text": "I- Oh.."
		},
		{
			"speed": 0.035,
			"portrait": "tord",
			"boxState": "normal",
			"expression": "talk",
			"text": "I get what's going on."
		},
		{
			"speed": 0.03,
			"portrait": "tord",
			"boxState": "normal",
			"expression": "talk",
			"text": "And let me guess, you snuck this in my pocket didn't you."
		},
		{
			"speed": 0.03,
			"portrait": "tord",
			"boxState": "normal",
			"expression": "talk",
			"text": "Whatever. I have plans I need to get to but, I can spare a few extra minutes."
		},
		{
			"speed": 0.035,
			"portrait": "bf",
			"boxState": "normal",
			"expression": "talk",
			"text": "Yeah!"
		},
		{
			"speed": 0.035,
			"portrait": "tord",
			"boxState": "normal",
			"expression": "talk",
			"text": "Let's do this then."
		}
	]
}